timingsutil/__init__.py
timingsutil/_metadata.py
timingsutil/daylight_savings.py
timingsutil/jdutil.py
timingsutil/stopwatch.py
timingsutil/throttle.py
timingsutil/time_constants.py
timingsutil/time_incrementer.py
timingsutil/timeout.py
timingsutil/unittests/__init__.py
timingsutil/unittests/test_stopwatch.py
timingsutil/unittests/test_throttle.py
timingsutil/unittests/test_time_incrementer.py
timingsutil/unittests/test_timeout.py
timingsutil-1.7.1.dist-info/LICENSE.txt
timingsutil-1.7.1.dist-info/METADATA
timingsutil-1.7.1.dist-info/WHEEL
timingsutil-1.7.1.dist-info/entry_points.txt
timingsutil-1.7.1.dist-info/top_level.txt
timingsutil-1.7.1.dist-info/RECORD
